MANIFEST.in
Makefile
README
RegionProposalGenerator-2.1.0.html
setup.py
ExamplesObjectDetection/README
ExamplesObjectDetection/multi_instance_object_detection.py
ExamplesObjectDetection/single_instance_object_detection.py
ExamplesRegionProposals/README
ExamplesRegionProposals/interactive_graph_based_segmentation.py
ExamplesRegionProposals/selective_search.py
ExamplesRegionProposals/torchvision_based_image_processing.py
ExamplesRegionProposals/torchvision_some_basic_transformations.py
ExamplesRegionProposals/color_blobs/color_blobs.jpg
ExamplesRegionProposals/color_blobs/selective_search.py
ExamplesRegionProposals/images/disk.jpg
ExamplesRegionProposals/images/london6.jpg
ExamplesRegionProposals/images/mondrian.jpg
ExamplesRegionProposals/images/polkadots.jpg
ExamplesRegionProposals/images/rect_with_4_colors.jpg
ExamplesRegionProposals/images/tulip0036.jpg
ExamplesRegionProposals/images/wallpic2.jpg
ExamplesRegionProposals/mondrian/README
ExamplesRegionProposals/mondrian/mondrian.jpg
ExamplesRegionProposals/mondrian/selective_search.py
ExamplesRegionProposals/wallpic2/selective_search.py
ExamplesRegionProposals/wallpic2/wallpic2.jpg
RegionProposalGenerator/RegionProposalGenerator.py
RegionProposalGenerator/__init__.py
RegionProposalGenerator.egg-info/PKG-INFO
RegionProposalGenerator.egg-info/SOURCES.txt
RegionProposalGenerator.egg-info/dependency_links.txt
RegionProposalGenerator.egg-info/top_level.txt
TestRegionProposalGenerator/RegionProposalGenerator.py
TestRegionProposalGenerator/Test.py
TestRegionProposalGenerator/TestImageConversion.py
TestRegionProposalGenerator/TestImageLoadingAndDataExtraction.py
TestRegionProposalGenerator/halfsun.jpg